codecheq/__init__.py
codecheq/analyzer.py
codecheq/config.py
codecheq/patcher.py
codecheq/patcher_backup.py
codecheq/prompt.py
codecheq/auth/__init__.py
codecheq/auth/client.py
codecheq/auth/config.py
codecheq/auth/exceptions.py
codecheq/auth/messages.py
codecheq/auth/verifier.py
codecheq/cli/__init__.py
codecheq/cli/main.py
codecheq/models/__init__.py
codecheq/models/analysis_result.py
codecheq/utils/__init__.py
codecheq/utils/file_filter.py
codecheq-0.1.9.dist-info/licenses/LICENSE
codecheq-0.1.9.dist-info/METADATA
codecheq-0.1.9.dist-info/WHEEL
codecheq-0.1.9.dist-info/entry_points.txt
codecheq-0.1.9.dist-info/top_level.txt
codecheq-0.1.9.dist-info/RECORD
